schema_builder/__init__.py
schema_builder/builder_ddl.py
schema_builder/builder_table_list.py
schema_builder-0.1.3.dist-info/LICENSE
schema_builder-0.1.3.dist-info/WHEEL
schema_builder-0.1.3.dist-info/METADATA
schema_builder-0.1.3.dist-info/RECORD
