Metadata-Version: 2.1
Name: schema-builder
Version: 0.1.3
Summary: Build JSON schemas from database tables.
Author: Jordan Williams
Author-email: jordan.wallace.williams@gmail.com
Requires-Python: >=3.8,<4.0
Classifier: Programming Language :: Python :: 3
Classifier: Programming Language :: Python :: 3.8
Classifier: Programming Language :: Python :: 3.9
